{
  "aws": {
    "region": "us-east-1"
  },
  "db": {
    "user": "audience_worker",
    "host": "localhost",
    "database": "jupiter",
    "password": "pwd_for_audience_worker",
    "port" :"5430"
  },
  "tables": {
    "audienceTable": "audience_data.audience",
    "audienceJoinTable": "audience_data.audience_account_join",
    "transactionTable": "transaction_data.core_transaction_ledger",
    "accountTable": "account_data.core_account_ledger",
    "boostTable": "boost_data.boost_account_status",
    "friendTable": "friend_data.core_friend_relationship"
  }
}